{
  "type": "FeatureCollection",
  "metadata": {
    "generated": 1720040437000,
    "url": "https://earthquake.usgs.gov/earthquakes/feed/v1.0/summary/2.5_day.geojson",
    "title": "USGS Magnitude 2.5+ Earthquakes, Past Day",
    "status": 200,
    "api": "1.10.3",
    "count": 41
  },
  "features": [
    {
      "type": "Feature",
      "properties": {
        "mag": 4.4,
        "place": "Vancouver Island, Canada region",
        "time": 1720036756539,
        "updated": 1720039956909,
        "tz": null,
        "url": "https://earthquake.usgs.gov/earthquakes/eventpage/us6000na4b",
        "detail": "https://earthquake.usgs.gov/earthquakes/feed/v1.0/detail/us6000na4b.geojson",
        "felt": 3,
        "cdi": 1,
        "mmi": null,
        "alert": null,
        "status": "reviewed",
        "tsunami": 1,
        "sig": 298,
        "net": "us",
        "code": "6000na4b",
        "ids": ",us6000na4b,at00sg2cuz,",
        "sources": ",us,at,",
        "types": ",dyfi,impact-link,origin,phase-data,",
        "nst": 36,
        "dmin": 2.131,
        "rms": 1.13,
        "gap": 154,
        "magType": "mb",
        "type": "earthquake",
        "title": "M 4.4 - Vancouver Island, Canada region"
      },
      "geometry": {
        "type": "Point",
        "coordinates": [
          -128.6736,
          48.5409,
          10
        ]
      },
      "id": "us6000na4b"
    },
    {
      "type": "Feature",
      "properties": {
        "mag": 4.4,
        "place": "Bonin Islands, Japan region",
        "time": 1720035068820,
        "updated": 1720036205040,
        "tz": null,
        "url": "https://earthquake.usgs.gov/earthquakes/eventpage/us6000na49",
        "detail": "https://earthquake.usgs.gov/earthquakes/feed/v1.0/detail/us6000na49.geojson",
        "felt": null,
        "cdi": null,
        "mmi": null,
        "alert": null,
        "status": "reviewed",
        "tsunami": 0,
        "sig": 298,
        "net": "us",
        "code": "6000na49",
        "ids": ",us6000na49,",
        "sources": ",us,",
        "types": ",origin,phase-data,",
        "nst": 24,
        "dmin": 1.113,
        "rms": 0.48,
        "gap": 138,
        "magType": "mb",
        "type": "earthquake",
        "title": "M 4.4 - Bonin Islands, Japan region"
      },
      "geometry": {
        "type": "Point",
        "coordinates": [
          143.0803,
          27.8762,
          16.867
        ]
      },
      "id": "us6000na49"
    },
    {
      "type": "Feature",
      "properties": {
        "mag": 5.3,
        "place": "39 km W of San Pedro de Atacama, Chile",
        "time": 1720030834677,
        "updated": 1720037521498,
        "tz": null,
        "url": "https://earthquake.usgs.gov/earthquakes/eventpage/usd0011dnn",
        "detail": "https://earthquake.usgs.gov/earthquakes/feed/v1.0/detail/usd0011dnn.geojson",
        "felt": 2,
        "cdi": 3.1,
        "mmi": null,
        "alert": null,
        "status": "reviewed",
        "tsunami": 0,
        "sig": 433,
        "net": "us",
        "code": "d0011dnn",
        "ids": ",usd0011dnn,",
        "sources": ",us,",
        "types": ",dyfi,origin,phase-data,",
        "nst": 103,
        "dmin": 0.371,
        "rms": 1.01,
        "gap": 56,
        "magType": "mww",
        "type": "earthquake",
        "title": "M 5.3 - 39 km W of San Pedro de Atacama, Chile"
      },
      "geometry": {
        "type": "Point",
        "coordinates": [
          -68.5811,
          -22.9565,
          93.864
        ]
      },
      "id": "usd0011dnn"
    },
    {
      "type": "Feature",
      "properties": {
        "mag": 3.01,
        "place": "93 km ESE of Maneadero, B.C., MX",
        "time": 1720023797900,
        "updated": 1720038016086,
        "tz": null,
        "url": "https://earthquake.usgs.gov/earthquakes/eventpage/ci40647423",
        "detail": "https://earthquake.usgs.gov/earthquakes/feed/v1.0/detail/ci40647423.geojson",
        "felt": null,
        "cdi": null,
        "mmi": null,
        "alert": null,
        "status": "reviewed",
        "tsunami": 0,
        "sig": 139,
        "net": "ci",
        "code": "40647423",
        "ids": ",ci40647423,",
        "sources": ",ci,",
        "types": ",nearby-cities,origin,phase-data,scitech-link,",
        "nst": 5,
        "dmin": 0.1574,
        "rms": 0.15,
        "gap": 127,
        "magType": "ml",
        "type": "earthquake",
        "title": "M 3.0 - 93 km ESE of Maneadero, B.C., MX"
      },
      "geometry": {
        "type": "Point",
        "coordinates": [
          -115.6285,
          31.476,
          4.86
        ]
      },
      "id": "ci40647423"
    },
    {
      "type": "Feature",
      "properties": {
        "mag": 2.51,
        "place": "10 km NE of Pāhala, Hawaii",
        "time": 1720021141690,
        "updated": 1720029010330,
        "tz": null,
        "url": "https://earthquake.usgs.gov/earthquakes/eventpage/hv74313511",
        "detail": "https://earthquake.usgs.gov/earthquakes/feed/v1.0/detail/hv74313511.geojson",
        "felt": null,
        "cdi": null,
        "mmi": null,
        "alert": null,
        "status": "reviewed",
        "tsunami": 0,
        "sig": 97,
        "net": "hv",
        "code": "74313511",
        "ids": ",hv74313511,",
        "sources": ",hv,",
        "types": ",origin,phase-data,",
        "nst": 60,
        "dmin": 0.02776,
        "rms": 0.13,
        "gap": 90,
        "magType": "ml",
        "type": "earthquake",
        "title": "M 2.5 - 10 km NE of Pāhala, Hawaii"
      },
      "geometry": {
        "type": "Point",
        "coordinates": [
          -155.399666666667,
          19.2653333333333,
          31.22
        ]
      },
      "id": "hv74313511"
    },
    {
      "type": "Feature",
      "properties": {
        "mag": 4.7,
        "place": "276 km WSW of Tual, Indonesia",
        "time": 1720020104700,
        "updated": 1720021150040,
        "tz": null,
        "url": "https://earthquake.usgs.gov/earthquakes/eventpage/us6000na1s",
        "detail": "https://earthquake.usgs.gov/earthquakes/feed/v1.0/detail/us6000na1s.geojson",
        "felt": null,
        "cdi": null,
        "mmi": null,
        "alert": null,
        "status": "reviewed",
        "tsunami": 0,
        "sig": 340,
        "net": "us",
        "code": "6000na1s",
        "ids": ",us6000na1s,",
        "sources": ",us,",
        "types": ",origin,phase-data,",
        "nst": 37,
        "dmin": 1.83,
        "rms": 0.59,
        "gap": 103,
        "magType": "mb",
        "type": "earthquake",
        "title": "M 4.7 - 276 km WSW of Tual, Indonesia"
      },
      "geometry": {
        "type": "Point",
        "coordinates": [
          130.3521,
          -6.3094,
          151.193
        ]
      },
      "id": "us6000na1s"
    },
    {
      "type": "Feature",
      "properties": {
        "mag": 2.7,
        "place": "40 km W of Anchor Point, Alaska",
        "time": 1720016880155,
        "updated": 1720016971965,
        "tz": null,
        "url": "https://earthquake.usgs.gov/earthquakes/eventpage/ak0248i6x6s1",
        "detail": "https://earthquake.usgs.gov/earthquakes/feed/v1.0/detail/ak0248i6x6s1.geojson",
        "felt": null,
        "cdi": null,
        "mmi": null,
        "alert": null,
        "status": "automatic",
        "tsunami": 0,
        "sig": 112,
        "net": "ak",
        "code": "0248i6x6s1",
        "ids": ",ak0248i6x6s1,",
        "sources": ",ak,",
        "types": ",origin,phase-data,",
        "nst": null,
        "dmin": null,
        "rms": 0.32,
        "gap": null,
        "magType": "ml",
        "type": "earthquake",
        "title": "M 2.7 - 40 km W of Anchor Point, Alaska"
      },
      "geometry": {
        "type": "Point",
        "coordinates": [
          -152.55,
          59.7659,
          88.7
        ]
      },
      "id": "ak0248i6x6s1"
    },
    {
      "type": "Feature",
      "properties": {
        "mag": 3,
        "place": "67 km SW of Miramichi, Canada",
        "time": 1720013969600,
        "updated": 1720035338333,
        "tz": null,
        "url": "https://earthquake.usgs.gov/earthquakes/eventpage/us6000na1e",
        "detail": "https://earthquake.usgs.gov/earthquakes/feed/v1.0/detail/us6000na1e.geojson",
        "felt": 13,
        "cdi": 4.3,
        "mmi": null,
        "alert": null,
        "status": "reviewed",
        "tsunami": 0,
        "sig": 144,
        "net": "us",
        "code": "6000na1e",
        "ids": ",us6000na1e,",
        "sources": ",us,",
        "types": ",dyfi,origin,phase-data,",
        "nst": 24,
        "dmin": 0.701,
        "rms": 0.4,
        "gap": 106,
        "magType": "mb_lg",
        "type": "earthquake",
        "title": "M 3.0 - 67 km SW of Miramichi, Canada"
      },
      "geometry": {
        "type": "Point",
        "coordinates": [
          -66.092,
          46.5761,
          11.614
        ]
      },
      "id": "us6000na1e"
    },
    {
      "type": "Feature",
      "properties": {
        "mag": 3.1,
        "place": "58 km N of Chickaloon, Alaska",
        "time": 1720013105950,
        "updated": 1720013367223,
        "tz": null,
        "url": "https://earthquake.usgs.gov/earthquakes/eventpage/ak0248i6bb43",
        "detail": "https://earthquake.usgs.gov/earthquakes/feed/v1.0/detail/ak0248i6bb43.geojson",
        "felt": null,
        "cdi": null,
        "mmi": null,
        "alert": null,
        "status": "automatic",
        "tsunami": 0,
        "sig": 148,
        "net": "ak",
        "code": "0248i6bb43",
        "ids": ",ak0248i6bb43,",
        "sources": ",ak,",
        "types": ",origin,phase-data,",
        "nst": null,
        "dmin": null,
        "rms": 0.75,
        "gap": null,
        "magType": "ml",
        "type": "earthquake",
        "title": "M 3.1 - 58 km N of Chickaloon, Alaska"
      },
      "geometry": {
        "type": "Point",
        "coordinates": [
          -148.4156,
          62.3245,
          0
        ]
      },
      "id": "ak0248i6bb43"
    },
    {
      "type": "Feature",
      "properties": {
        "mag": 3.2,
        "place": "60 km S of Cantwell, Alaska",
        "time": 1720013098625,
        "updated": 1720013214265,
        "tz": null,
        "url": "https://earthquake.usgs.gov/earthquakes/eventpage/ak0248i6b3v9",
        "detail": "https://earthquake.usgs.gov/earthquakes/feed/v1.0/detail/ak0248i6b3v9.geojson",
        "felt": null,
        "cdi": null,
        "mmi": null,
        "alert": null,
        "status": "automatic",
        "tsunami": 0,
        "sig": 158,
        "net": "ak",
        "code": "0248i6b3v9",
        "ids": ",ak0248i6b3v9,",
        "sources": ",ak,",
        "types": ",origin,phase-data,",
        "nst": null,
        "dmin": null,
        "rms": 0.97,
        "gap": null,
        "magType": "ml",
        "type": "earthquake",
        "title": "M 3.2 - 60 km S of Cantwell, Alaska"
      },
      "geometry": {
        "type": "Point",
        "coordinates": [
          -148.9396,
          62.8471,
          4.4
        ]
      },
      "id": "ak0248i6b3v9"
    },
    {
      "type": "Feature",
      "properties": {
        "mag": 5.3,
        "place": "78 km NNE of Loreto, Mexico",
        "time": 1720007067795,
        "updated": 1720017750150,
        "tz": null,
        "url": "https://earthquake.usgs.gov/earthquakes/eventpage/us6000na0d",
        "detail": "https://earthquake.usgs.gov/earthquakes/feed/v1.0/detail/us6000na0d.geojson",
        "felt": 3,
        "cdi": 3.4,
        "mmi": null,
        "alert": null,
        "status": "reviewed",
        "tsunami": 0,
        "sig": 433,
        "net": "us",
        "code": "6000na0d",
        "ids": ",us6000na0d,",
        "sources": ",us,",
        "types": ",dyfi,moment-tensor,origin,phase-data,",
        "nst": 61,
        "dmin": 1.318,
        "rms": 1.04,
        "gap": 184,
        "magType": "mww",
        "type": "earthquake",
        "title": "M 5.3 - 78 km NNE of Loreto, Mexico"
      },
      "geometry": {
        "type": "Point",
        "coordinates": [
          -110.9773,
          26.6344,
          10
        ]
      },
      "id": "us6000na0d"
    },
    {
      "type": "Feature",
      "properties": {
        "mag": 4.3,
        "place": "Fiji region",
        "time": 1720003277849,
        "updated": 1720004346040,
        "tz": null,
        "url": "https://earthquake.usgs.gov/earthquakes/eventpage/us6000na0a",
        "detail": "https://earthquake.usgs.gov/earthquakes/feed/v1.0/detail/us6000na0a.geojson",
        "felt": null,
        "cdi": null,
        "mmi": null,
        "alert": null,
        "status": "reviewed",
        "tsunami": 0,
        "sig": 284,
        "net": "us",
        "code": "6000na0a",
        "ids": ",us6000na0a,",
        "sources": ",us,",
        "types": ",origin,phase-data,",
        "nst": 75,
        "dmin": 3.465,
        "rms": 0.75,
        "gap": 41,
        "magType": "mb",
        "type": "earthquake",
        "title": "M 4.3 - Fiji region"
      },
      "geometry": {
        "type": "Point",
        "coordinates": [
          -177.8168,
          -18.7142,
          490.432
        ]
      },
      "id": "us6000na0a"
    },
    {
      "type": "Feature",
      "properties": {
        "mag": 2.65,
        "place": "12 km ENE of Pāhala, Hawaii",
        "time": 1719996179520,
        "updated": 1720033814520,
        "tz": null,
        "url": "https://earthquake.usgs.gov/earthquakes/eventpage/hv74312951",
        "detail": "https://earthquake.usgs.gov/earthquakes/feed/v1.0/detail/hv74312951.geojson",
        "felt": null,
        "cdi": null,
        "mmi": null,
        "alert": null,
        "status": "reviewed",
        "tsunami": 0,
        "sig": 108,
        "net": "hv",
        "code": "74312951",
        "ids": ",hv74312951,",
        "sources": ",hv,",
        "types": ",origin,phase-data,",
        "nst": 59,
        "dmin": 0.03008,
        "rms": 0.12,
        "gap": 153,
        "magType": "ml",
        "type": "earthquake",
        "title": "M 2.7 - 12 km ENE of Pāhala, Hawaii"
      },
      "geometry": {
        "type": "Point",
        "coordinates": [
          -155.366166666667,
          19.2321666666667,
          33.87
        ]
      },
      "id": "hv74312951"
    },
    {
      "type": "Feature",
      "properties": {
        "mag": 2.48,
        "place": "6 km S of Volcano, Hawaii",
        "time": 1719993082310,
        "updated": 1719995736040,
        "tz": null,
        "url": "https://earthquake.usgs.gov/earthquakes/eventpage/hv74312886",
        "detail": "https://earthquake.usgs.gov/earthquakes/feed/v1.0/detail/hv74312886.geojson",
        "felt": 1,
        "cdi": 2.2,
        "mmi": null,
        "alert": null,
        "status": "reviewed",
        "tsunami": 0,
        "sig": 95,
        "net": "hv",
        "code": "74312886",
        "ids": ",hv74312886,us6000n9zr,",
        "sources": ",hv,us,",
        "types": ",dyfi,origin,phase-data,",
        "nst": 49,
        "dmin": 0.00989,
        "rms": 0.1,
        "gap": 40,
        "magType": "ml",
        "type": "earthquake",
        "title": "M 2.5 - 6 km S of Volcano, Hawaii"
      },
      "geometry": {
        "type": "Point",
        "coordinates": [
          -155.241166666667,
          19.388,
          1.89
        ]
      },
      "id": "hv74312886"
    },
    {
      "type": "Feature",
      "properties": {
        "mag": 4.8,
        "place": "124 km ESE of Lata, Solomon Islands",
        "time": 1719992128283,
        "updated": 1719994301040,
        "tz": null,
        "url": "https://earthquake.usgs.gov/earthquakes/eventpage/us6000n9zq",
        "detail": "https://earthquake.usgs.gov/earthquakes/feed/v1.0/detail/us6000n9zq.geojson",
        "felt": null,
        "cdi": null,
        "mmi": null,
        "alert": null,
        "status": "reviewed",
        "tsunami": 0,
        "sig": 354,
        "net": "us",
        "code": "6000n9zq",
        "ids": ",us6000n9zq,",
        "sources": ",us,",
        "types": ",origin,phase-data,",
        "nst": 27,
        "dmin": 9.579,
        "rms": 0.7,
        "gap": 116,
        "magType": "mb",
        "type": "earthquake",
        "title": "M 4.8 - 124 km ESE of Lata, Solomon Islands"
      },
      "geometry": {
        "type": "Point",
        "coordinates": [
          166.8124,
          -11.231,
          10
        ]
      },
      "id": "us6000n9zq"
    },
    {
      "type": "Feature",
      "properties": {
        "mag": 5.2,
        "place": "southern Mid-Atlantic Ridge",
        "time": 1719991048285,
        "updated": 1719992064040,
        "tz": null,
        "url": "https://earthquake.usgs.gov/earthquakes/eventpage/us6000n9zp",
        "detail": "https://earthquake.usgs.gov/earthquakes/feed/v1.0/detail/us6000n9zp.geojson",
        "felt": null,
        "cdi": null,
        "mmi": null,
        "alert": null,
        "status": "reviewed",
        "tsunami": 0,
        "sig": 416,
        "net": "us",
        "code": "6000n9zp",
        "ids": ",us6000n9zp,",
        "sources": ",us,",
        "types": ",origin,phase-data,",
        "nst": 30,
        "dmin": 17.72,
        "rms": 0.73,
        "gap": 91,
        "magType": "mb",
        "type": "earthquake",
        "title": "M 5.2 - southern Mid-Atlantic Ridge"
      },
      "geometry": {
        "type": "Point",
        "coordinates": [
          -2.4486,
          -54.019,
          10
        ]
      },
      "id": "us6000n9zp"
    },
    {
      "type": "Feature",
      "properties": {
        "mag": 4.4,
        "place": "south of the Fiji Islands",
        "time": 1719990490052,
        "updated": 1719994617040,
        "tz": null,
        "url": "https://earthquake.usgs.gov/earthquakes/eventpage/us6000n9zn",
        "detail": "https://earthquake.usgs.gov/earthquakes/feed/v1.0/detail/us6000n9zn.geojson",
        "felt": null,
        "cdi": null,
        "mmi": null,
        "alert": null,
        "status": "reviewed",
        "tsunami": 0,
        "sig": 298,
        "net": "us",
        "code": "6000n9zn",
        "ids": ",us6000n9zn,",
        "sources": ",us,",
        "types": ",origin,phase-data,",
        "nst": 54,
        "dmin": 4.212,
        "rms": 0.78,
        "gap": 96,
        "magType": "mb",
        "type": "earthquake",
        "title": "M 4.4 - south of the Fiji Islands"
      },
      "geometry": {
        "type": "Point",
        "coordinates": [
          -179.4002,
          -22.7806,
          519.163
        ]
      },
      "id": "us6000n9zn"
    },
    {
      "type": "Feature",
      "properties": {
        "mag": 3.22,
        "place": "3 km SW of Fuig, Puerto Rico",
        "time": 1719987618930,
        "updated": 1719996237040,
        "tz": null,
        "url": "https://earthquake.usgs.gov/earthquakes/eventpage/pr2024185000",
        "detail": "https://earthquake.usgs.gov/earthquakes/feed/v1.0/detail/pr2024185000.geojson",
        "felt": null,
        "cdi": null,
        "mmi": null,
        "alert": null,
        "status": "reviewed",
        "tsunami": 0,
        "sig": 160,
        "net": "pr",
        "code": "2024185000",
        "ids": ",us6000n9zk,pr2024185000,",
        "sources": ",us,pr,",
        "types": ",origin,phase-data,",
        "nst": 15,
        "dmin": 0.1731,
        "rms": 0.17,
        "gap": 181,
        "magType": "md",
        "type": "earthquake",
        "title": "M 3.2 - 3 km SW of Fuig, Puerto Rico"
      },
      "geometry": {
        "type": "Point",
        "coordinates": [
          -66.9401,
          17.971,
          4
        ]
      },
      "id": "pr2024185000"
    },
    {
      "type": "Feature",
      "properties": {
        "mag": 2.67,
        "place": "6 km S of Volcano, Hawaii",
        "time": 1719986235640,
        "updated": 1720037088190,
        "tz": null,
        "url": "https://earthquake.usgs.gov/earthquakes/eventpage/hv74312666",
        "detail": "https://earthquake.usgs.gov/earthquakes/feed/v1.0/detail/hv74312666.geojson",
        "felt": null,
        "cdi": null,
        "mmi": null,
        "alert": null,
        "status": "reviewed",
        "tsunami": 0,
        "sig": 110,
        "net": "hv",
        "code": "74312666",
        "ids": ",hv74312666,",
        "sources": ",hv,",
        "types": ",origin,phase-data,",
        "nst": 38,
        "dmin": 0.009266,
        "rms": 0.1,
        "gap": 75,
        "magType": "ml",
        "type": "earthquake",
        "title": "M 2.7 - 6 km S of Volcano, Hawaii"
      },
      "geometry": {
        "type": "Point",
        "coordinates": [
          -155.236833333333,
          19.3821666666667,
          1.96
        ]
      },
      "id": "hv74312666"
    },
    {
      "type": "Feature",
      "properties": {
        "mag": 2.67,
        "place": "17 km WNW of Hāwī, Hawaii",
        "time": 1719985302000,
        "updated": 1719985484580,
        "tz": null,
        "url": "https://earthquake.usgs.gov/earthquakes/eventpage/hv74312646",
        "detail": "https://earthquake.usgs.gov/earthquakes/feed/v1.0/detail/hv74312646.geojson",
        "felt": null,
        "cdi": null,
        "mmi": null,
        "alert": null,
        "status": "automatic",
        "tsunami": 0,
        "sig": 110,
        "net": "hv",
        "code": "74312646",
        "ids": ",hv74312646,",
        "sources": ",hv,",
        "types": ",origin,phase-data,",
        "nst": 49,
        "dmin": 0.374,
        "rms": 0.209999993,
        "gap": 145,
        "magType": "ml",
        "type": "earthquake",
        "title": "M 2.7 - 17 km WNW of Hāwī, Hawaii"
      },
      "geometry": {
        "type": "Point",
        "coordinates": [
          -155.994506835938,
          20.2803325653076,
          10.1700000762939
        ]
      },
      "id": "hv74312646"
    },
    {
      "type": "Feature",
      "properties": {
        "mag": 4.1,
        "place": "76 km WNW of Ollagüe, Chile",
        "time": 1719981368031,
        "updated": 1719982217040,
        "tz": null,
        "url": "https://earthquake.usgs.gov/earthquakes/eventpage/us6000n9z0",
        "detail": "https://earthquake.usgs.gov/earthquakes/feed/v1.0/detail/us6000n9z0.geojson",
        "felt": null,
        "cdi": null,
        "mmi": null,
        "alert": null,
        "status": "reviewed",
        "tsunami": 0,
        "sig": 259,
        "net": "us",
        "code": "6000n9z0",
        "ids": ",us6000n9z0,",
        "sources": ",us,",
        "types": ",origin,phase-data,",
        "nst": 17,
        "dmin": 0.532,
        "rms": 0.44,
        "gap": 73,
        "magType": "mb",
        "type": "earthquake",
        "title": "M 4.1 - 76 km WNW of Ollagüe, Chile"
      },
      "geometry": {
        "type": "Point",
        "coordinates": [
          -68.9278,
          -20.943,
          104.182
        ]
      },
      "id": "us6000n9z0"
    },
    {
      "type": "Feature",
      "properties": {
        "mag": 2.57,
        "place": "19 km NNE of Deep Springs, CA",
        "time": 1719975177480,
        "updated": 1720023553056,
        "tz": null,
        "url": "https://earthquake.usgs.gov/earthquakes/eventpage/nc75030031",
        "detail": "https://earthquake.usgs.gov/earthquakes/feed/v1.0/detail/nc75030031.geojson",
        "felt": null,
        "cdi": null,
        "mmi": null,
        "alert": null,
        "status": "reviewed",
        "tsunami": 0,
        "sig": 102,
        "net": "nc",
        "code": "75030031",
        "ids": ",nc75030031,nn00880295,",
        "sources": ",nc,nn,",
        "types": ",nearby-cities,origin,phase-data,",
        "nst": 28,
        "dmin": 0.3191,
        "rms": 0.07,
        "gap": 142,
        "magType": "md",
        "type": "earthquake",
        "title": "M 2.6 - 19 km NNE of Deep Springs, CA"
      },
      "geometry": {
        "type": "Point",
        "coordinates": [
          -117.966666666667,
          37.5456666666667,
          2.8
        ]
      },
      "id": "nc75030031"
    },
    {
      "type": "Feature",
      "properties": {
        "mag": 4.7,
        "place": "48 km ESE of Gilgit, Pakistan",
        "time": 1719974571458,
        "updated": 1719981535817,
        "tz": null,
        "url": "https://earthquake.usgs.gov/earthquakes/eventpage/us6000n9yf",
        "detail": "https://earthquake.usgs.gov/earthquakes/feed/v1.0/detail/us6000n9yf.geojson",
        "felt": 2,
        "cdi": 2.4,
        "mmi": null,
        "alert": null,
        "status": "reviewed",
        "tsunami": 0,
        "sig": 340,
        "net": "us",
        "code": "6000n9yf",
        "ids": ",us6000n9yf,",
        "sources": ",us,",
        "types": ",dyfi,origin,phase-data,",
        "nst": 50,
        "dmin": 4.437,
        "rms": 0.69,
        "gap": 251,
        "magType": "mb",
        "type": "earthquake",
        "title": "M 4.7 - 48 km ESE of Gilgit, Pakistan"
      },
      "geometry": {
        "type": "Point",
        "coordinates": [
          74.7838,
          35.7192,
          10
        ]
      },
      "id": "us6000n9yf"
    },
    {
      "type": "Feature",
      "properties": {
        "mag": 5,
        "place": "North Pacific Ocean",
        "time": 1719973222957,
        "updated": 1719974282040,
        "tz": null,
        "url": "https://earthquake.usgs.gov/earthquakes/eventpage/us6000n9yc",
        "detail": "https://earthquake.usgs.gov/earthquakes/feed/v1.0/detail/us6000n9yc.geojson",
        "felt": null,
        "cdi": null,
        "mmi": null,
        "alert": null,
        "status": "reviewed",
        "tsunami": 0,
        "sig": 385,
        "net": "us",
        "code": "6000n9yc",
        "ids": ",us6000n9yc,",
        "sources": ",us,",
        "types": ",origin,phase-data,",
        "nst": 63,
        "dmin": 9.042,
        "rms": 1.05,
        "gap": 137,
        "magType": "mb",
        "type": "earthquake",
        "title": "M 5.0 - North Pacific Ocean"
      },
      "geometry": {
        "type": "Point",
        "coordinates": [
          156.5284,
          44.0978,
          10
        ]
      },
      "id": "us6000n9yc"
    },
    {
      "type": "Feature",
      "properties": {
        "mag": 2.91,
        "place": "6 km SSE of Maria Antonia, Puerto Rico",
        "time": 1719972287060,
        "updated": 1719973081090,
        "tz": null,
        "url": "https://earthquake.usgs.gov/earthquakes/eventpage/pr71454538",
        "detail": "https://earthquake.usgs.gov/earthquakes/feed/v1.0/detail/pr71454538.geojson",
        "felt": null,
        "cdi": null,
        "mmi": null,
        "alert": null,
        "status": "reviewed",
        "tsunami": 0,
        "sig": 130,
        "net": "pr",
        "code": "71454538",
        "ids": ",pr71454538,",
        "sources": ",pr,",
        "types": ",origin,phase-data,",
        "nst": 19,
        "dmin": 0.04396,
        "rms": 0.18,
        "gap": 196,
        "magType": "md",
        "type": "earthquake",
        "title": "M 2.9 - 6 km SSE of Maria Antonia, Puerto Rico"
      },
      "geometry": {
        "type": "Point",
        "coordinates": [
          -66.8571666666667,
          17.9295,
          10.41
        ]
      },
      "id": "pr71454538"
    },
    {
      "type": "Feature",
      "properties": {
        "mag": 4.3,
        "place": "167 km SW of Nikolski, Alaska",
        "time": 1719966493310,
        "updated": 1719980457295,
        "tz": null,
        "url": "https://earthquake.usgs.gov/earthquakes/eventpage/us6000n9y1",
        "detail": "https://earthquake.usgs.gov/earthquakes/feed/v1.0/detail/us6000n9y1.geojson",
        "felt": null,
        "cdi": null,
        "mmi": 2.116,
        "alert": null,
        "status": "reviewed",
        "tsunami": 0,
        "sig": 284,
        "net": "us",
        "code": "6000n9y1",
        "ids": ",us6000n9y1,ak0248hyl3j0,",
        "sources": ",us,ak,",
        "types": ",moment-tensor,origin,phase-data,shakemap,",
        "nst": 59,
        "dmin": 1,
        "rms": 0.84,
        "gap": 177,
        "magType": "mwr",
        "type": "earthquake",
        "title": "M 4.3 - 167 km SW of Nikolski, Alaska"
      },
      "geometry": {
        "type": "Point",
        "coordinates": [
          -170.8826,
          52.0828,
          35.338
        ]
      },
      "id": "us6000n9y1"
    },
    {
      "type": "Feature",
      "properties": {
        "mag": 4.6,
        "place": "166 km SW of Nikolski, Alaska",
        "time": 1719966040000,
        "updated": 1719979905414,
        "tz": null,
        "url": "https://earthquake.usgs.gov/earthquakes/eventpage/us6000n9xz",
        "detail": "https://earthquake.usgs.gov/earthquakes/feed/v1.0/detail/us6000n9xz.geojson",
        "felt": null,
        "cdi": null,
        "mmi": 2.421,
        "alert": null,
        "status": "reviewed",
        "tsunami": 0,
        "sig": 326,
        "net": "us",
        "code": "6000n9xz",
        "ids": ",us6000n9xz,ak0248hyjksa,",
        "sources": ",us,ak,",
        "types": ",moment-tensor,origin,phase-data,shakemap,",
        "nst": 90,
        "dmin": 0.995,
        "rms": 0.87,
        "gap": 136,
        "magType": "mwr",
        "type": "earthquake",
        "title": "M 4.6 - 166 km SW of Nikolski, Alaska"
      },
      "geometry": {
        "type": "Point",
        "coordinates": [
          -170.9106,
          52.1088,
          43.718
        ]
      },
      "id": "us6000n9xz"
    },
    {
      "type": "Feature",
      "properties": {
        "mag": 2.8,
        "place": "54 km NW of Toyah, Texas",
        "time": 1719965415645,
        "updated": 1720033495728,
        "tz": null,
        "url": "https://earthquake.usgs.gov/earthquakes/eventpage/tx2024myex",
        "detail": "https://earthquake.usgs.gov/earthquakes/feed/v1.0/detail/tx2024myex.geojson",
        "felt": null,
        "cdi": null,
        "mmi": null,
        "alert": null,
        "status": "reviewed",
        "tsunami": 0,
        "sig": 121,
        "net": "tx",
        "code": "2024myex",
        "ids": ",us6000n9xx,tx2024myex,",
        "sources": ",us,tx,",
        "types": ",origin,phase-data,",
        "nst": 33,
        "dmin": 0.1,
        "rms": 0.1,
        "gap": 68,
        "magType": "ml",
        "type": "earthquake",
        "title": "M 2.8 - 54 km NW of Toyah, Texas"
      },
      "geometry": {
        "type": "Point",
        "coordinates": [
          -104.19,
          31.672,
          6.7151
        ]
      },
      "id": "tx2024myex"
    },
    {
      "type": "Feature",
      "properties": {
        "mag": 3.5,
        "place": "54 km NW of Toyah, Texas",
        "time": 1719965075395,
        "updated": 1720017667729,
        "tz": null,
        "url": "https://earthquake.usgs.gov/earthquakes/eventpage/tx2024myet",
        "detail": "https://earthquake.usgs.gov/earthquakes/feed/v1.0/detail/tx2024myet.geojson",
        "felt": null,
        "cdi": null,
        "mmi": 3.912,
        "alert": null,
        "status": "reviewed",
        "tsunami": 0,
        "sig": 188,
        "net": "tx",
        "code": "2024myet",
        "ids": ",us6000n9xs,tx2024myet,",
        "sources": ",us,tx,",
        "types": ",origin,phase-data,shakemap,",
        "nst": 32,
        "dmin": 0.1,
        "rms": 0.1,
        "gap": 62,
        "magType": "ml",
        "type": "earthquake",
        "title": "M 3.5 - 54 km NW of Toyah, Texas"
      },
      "geometry": {
        "type": "Point",
        "coordinates": [
          -104.19,
          31.666,
          5.4077
        ]
      },
      "id": "tx2024myet"
    },
    {
      "type": "Feature",
      "properties": {
        "mag": 2.5,
        "place": "36 km N of Lowman, Idaho",
        "time": 1719963950235,
        "updated": 1719973514040,
        "tz": null,
        "url": "https://earthquake.usgs.gov/earthquakes/eventpage/us6000n9xn",
        "detail": "https://earthquake.usgs.gov/earthquakes/feed/v1.0/detail/us6000n9xn.geojson",
        "felt": null,
        "cdi": null,
        "mmi": null,
        "alert": null,
        "status": "reviewed",
        "tsunami": 0,
        "sig": 96,
        "net": "us",
        "code": "6000n9xn",
        "ids": ",us6000n9xn,",
        "sources": ",us,",
        "types": ",origin,phase-data,",
        "nst": 24,
        "dmin": 0.591,
        "rms": 1.03,
        "gap": 56,
        "magType": "ml",
        "type": "earthquake",
        "title": "M 2.5 - 36 km N of Lowman, Idaho"
      },
      "geometry": {
        "type": "Point",
        "coordinates": [
          -115.5573,
          44.4047,
          6.721
        ]
      },
      "id": "us6000n9xn"
    },
    {
      "type": "Feature",
      "properties": {
        "mag": 4.4,
        "place": "31 km WNW of Finschhafen, Papua New Guinea",
        "time": 1719963705395,
        "updated": 1720006194560,
        "tz": null,
        "url": "https://earthquake.usgs.gov/earthquakes/eventpage/us6000n9xp",
        "detail": "https://earthquake.usgs.gov/earthquakes/feed/v1.0/detail/us6000n9xp.geojson",
        "felt": 1,
        "cdi": 2,
        "mmi": null,
        "alert": null,
        "status": "reviewed",
        "tsunami": 0,
        "sig": 298,
        "net": "us",
        "code": "6000n9xp",
        "ids": ",us6000n9xp,",
        "sources": ",us,",
        "types": ",dyfi,origin,phase-data,",
        "nst": 21,
        "dmin": 2.949,
        "rms": 1.1,
        "gap": 230,
        "magType": "mb",
        "type": "earthquake",
        "title": "M 4.4 - 31 km WNW of Finschhafen, Papua New Guinea"
      },
      "geometry": {
        "type": "Point",
        "coordinates": [
          147.5756,
          -6.4657,
          52.645
        ]
      },
      "id": "us6000n9xp"
    },
    {
      "type": "Feature",
      "properties": {
        "mag": 2.9,
        "place": "54 km NW of Toyah, Texas",
        "time": 1719963684994,
        "updated": 1719965913040,
        "tz": null,
        "url": "https://earthquake.usgs.gov/earthquakes/eventpage/tx2024mydy",
        "detail": "https://earthquake.usgs.gov/earthquakes/feed/v1.0/detail/tx2024mydy.geojson",
        "felt": null,
        "cdi": null,
        "mmi": null,
        "alert": null,
        "status": "reviewed",
        "tsunami": 0,
        "sig": 129,
        "net": "tx",
        "code": "2024mydy",
        "ids": ",us6000n9xw,tx2024mydy,",
        "sources": ",us,tx,",
        "types": ",origin,phase-data,",
        "nst": 23,
        "dmin": 0.1,
        "rms": 0.1,
        "gap": 62,
        "magType": "ml",
        "type": "earthquake",
        "title": "M 2.9 - 54 km NW of Toyah, Texas"
      },
      "geometry": {
        "type": "Point",
        "coordinates": [
          -104.192,
          31.666,
          5.1001
        ]
      },
      "id": "tx2024mydy"
    },
    {
      "type": "Feature",
      "properties": {
        "mag": 3.7,
        "place": "54 km NW of Toyah, Texas",
        "time": 1719963599741,
        "updated": 1720017011498,
        "tz": null,
        "url": "https://earthquake.usgs.gov/earthquakes/eventpage/tx2024mydx",
        "detail": "https://earthquake.usgs.gov/earthquakes/feed/v1.0/detail/tx2024mydx.geojson",
        "felt": null,
        "cdi": null,
        "mmi": 4.16,
        "alert": null,
        "status": "reviewed",
        "tsunami": 0,
        "sig": 211,
        "net": "tx",
        "code": "2024mydx",
        "ids": ",us6000n9xf,tx2024mydx,",
        "sources": ",us,tx,",
        "types": ",moment-tensor,origin,phase-data,shakemap,",
        "nst": 32,
        "dmin": 0.1,
        "rms": 0.1,
        "gap": 61,
        "magType": "ml",
        "type": "earthquake",
        "title": "M 3.7 - 54 km NW of Toyah, Texas"
      },
      "geometry": {
        "type": "Point",
        "coordinates": [
          -104.189,
          31.67,
          5.946
        ]
      },
      "id": "tx2024mydx"
    },
    {
      "type": "Feature",
      "properties": {
        "mag": 4.5,
        "place": "Fiji region",
        "time": 1719962579586,
        "updated": 1719963707040,
        "tz": null,
        "url": "https://earthquake.usgs.gov/earthquakes/eventpage/us6000n9xc",
        "detail": "https://earthquake.usgs.gov/earthquakes/feed/v1.0/detail/us6000n9xc.geojson",
        "felt": null,
        "cdi": null,
        "mmi": null,
        "alert": null,
        "status": "reviewed",
        "tsunami": 0,
        "sig": 312,
        "net": "us",
        "code": "6000n9xc",
        "ids": ",us6000n9xc,",
        "sources": ",us,",
        "types": ",origin,phase-data,",
        "nst": 44,
        "dmin": 3.331,
        "rms": 0.84,
        "gap": 93,
        "magType": "mb",
        "type": "earthquake",
        "title": "M 4.5 - Fiji region"
      },
      "geometry": {
        "type": "Point",
        "coordinates": [
          -178.765,
          -20.987,
          620.597
        ]
      },
      "id": "us6000n9xc"
    },
    {
      "type": "Feature",
      "properties": {
        "mag": 3.1,
        "place": "54 km NW of Toyah, Texas",
        "time": 1719961117992,
        "updated": 1719962778905,
        "tz": null,
        "url": "https://earthquake.usgs.gov/earthquakes/eventpage/tx2024mycm",
        "detail": "https://earthquake.usgs.gov/earthquakes/feed/v1.0/detail/tx2024mycm.geojson",
        "felt": null,
        "cdi": null,
        "mmi": null,
        "alert": null,
        "status": "reviewed",
        "tsunami": 0,
        "sig": 148,
        "net": "tx",
        "code": "2024mycm",
        "ids": ",us6000n9x8,tx2024mycm,",
        "sources": ",us,tx,",
        "types": ",origin,phase-data,",
        "nst": 36,
        "dmin": 0.1,
        "rms": 0.1,
        "gap": 61,
        "magType": "ml",
        "type": "earthquake",
        "title": "M 3.1 - 54 km NW of Toyah, Texas"
      },
      "geometry": {
        "type": "Point",
        "coordinates": [
          -104.193,
          31.671,
          5.9204
        ]
      },
      "id": "tx2024mycm"
    },
    {
      "type": "Feature",
      "properties": {
        "mag": 2.5,
        "place": "54 km NW of Toyah, Texas",
        "time": 1719960840250,
        "updated": 1720025166624,
        "tz": null,
        "url": "https://earthquake.usgs.gov/earthquakes/eventpage/tx2024mycj",
        "detail": "https://earthquake.usgs.gov/earthquakes/feed/v1.0/detail/tx2024mycj.geojson",
        "felt": null,
        "cdi": null,
        "mmi": null,
        "alert": null,
        "status": "reviewed",
        "tsunami": 0,
        "sig": 96,
        "net": "tx",
        "code": "2024mycj",
        "ids": ",us6000n9x6,tx2024mycj,",
        "sources": ",us,tx,",
        "types": ",origin,phase-data,",
        "nst": 31,
        "dmin": 0.1,
        "rms": 0.1,
        "gap": 61,
        "magType": "ml",
        "type": "earthquake",
        "title": "M 2.5 - 54 km NW of Toyah, Texas"
      },
      "geometry": {
        "type": "Point",
        "coordinates": [
          -104.192,
          31.669,
          5.6384
        ]
      },
      "id": "tx2024mycj"
    },
    {
      "type": "Feature",
      "properties": {
        "mag": 4.5,
        "place": "59 km WSW of Illapel, Chile",
        "time": 1719960165287,
        "updated": 1719961463040,
        "tz": null,
        "url": "https://earthquake.usgs.gov/earthquakes/eventpage/us6000n9x5",
        "detail": "https://earthquake.usgs.gov/earthquakes/feed/v1.0/detail/us6000n9x5.geojson",
        "felt": null,
        "cdi": null,
        "mmi": null,
        "alert": null,
        "status": "reviewed",
        "tsunami": 0,
        "sig": 312,
        "net": "us",
        "code": "6000n9x5",
        "ids": ",us6000n9x5,",
        "sources": ",us,",
        "types": ",origin,phase-data,",
        "nst": 48,
        "dmin": 1.088,
        "rms": 0.96,
        "gap": 79,
        "magType": "mb",
        "type": "earthquake",
        "title": "M 4.5 - 59 km WSW of Illapel, Chile"
      },
      "geometry": {
        "type": "Point",
        "coordinates": [
          -71.7805,
          -31.758,
          41.509
        ]
      },
      "id": "us6000n9x5"
    },
    {
      "type": "Feature",
      "properties": {
        "mag": 4.6,
        "place": "36 km NNW of Luwuk, Indonesia",
        "time": 1719958046195,
        "updated": 1719959336040,
        "tz": null,
        "url": "https://earthquake.usgs.gov/earthquakes/eventpage/us6000n9x1",
        "detail": "https://earthquake.usgs.gov/earthquakes/feed/v1.0/detail/us6000n9x1.geojson",
        "felt": null,
        "cdi": null,
        "mmi": null,
        "alert": null,
        "status": "reviewed",
        "tsunami": 0,
        "sig": 326,
        "net": "us",
        "code": "6000n9x1",
        "ids": ",us6000n9x1,",
        "sources": ",us,",
        "types": ",origin,phase-data,",
        "nst": 38,
        "dmin": 2.576,
        "rms": 1.13,
        "gap": 54,
        "magType": "mb",
        "type": "earthquake",
        "title": "M 4.6 - 36 km NNW of Luwuk, Indonesia"
      },
      "geometry": {
        "type": "Point",
        "coordinates": [
          122.6854,
          -0.6364,
          10
        ]
      },
      "id": "us6000n9x1"
    },
    {
      "type": "Feature",
      "properties": {
        "mag": 4.3,
        "place": "north of Svalbard",
        "time": 1719956170176,
        "updated": 1719957405040,
        "tz": null,
        "url": "https://earthquake.usgs.gov/earthquakes/eventpage/us6000n9wy",
        "detail": "https://earthquake.usgs.gov/earthquakes/feed/v1.0/detail/us6000n9wy.geojson",
        "felt": null,
        "cdi": null,
        "mmi": null,
        "alert": null,
        "status": "reviewed",
        "tsunami": 0,
        "sig": 284,
        "net": "us",
        "code": "6000n9wy",
        "ids": ",us6000n9wy,",
        "sources": ",us,",
        "types": ",origin,phase-data,",
        "nst": 22,
        "dmin": 5.436,
        "rms": 1.07,
        "gap": 84,
        "magType": "mb",
        "type": "earthquake",
        "title": "M 4.3 - north of Svalbard"
      },
      "geometry": {
        "type": "Point",
        "coordinates": [
          -3.3504,
          83.8535,
          10
        ]
      },
      "id": "us6000n9wy"
    },
    {
      "type": "Feature",
      "properties": {
        "mag": 3.2,
        "place": "69 km NW of San Antonio, Puerto Rico",
        "time": 1719955699290,
        "updated": 1719958908340,
        "tz": null,
        "url": "https://earthquake.usgs.gov/earthquakes/eventpage/pr71454503",
        "detail": "https://earthquake.usgs.gov/earthquakes/feed/v1.0/detail/pr71454503.geojson",
        "felt": null,
        "cdi": null,
        "mmi": null,
        "alert": null,
        "status": "reviewed",
        "tsunami": 0,
        "sig": 158,
        "net": "pr",
        "code": "71454503",
        "ids": ",us6000n9w4,pr71454503,",
        "sources": ",us,pr,",
        "types": ",origin,phase-data,",
        "nst": 17,
        "dmin": 0.8198,
        "rms": 0.25,
        "gap": 194,
        "magType": "md",
        "type": "earthquake",
        "title": "M 3.2 - 69 km NW of San Antonio, Puerto Rico"
      },
      "geometry": {
        "type": "Point",
        "coordinates": [
          -67.5585,
          18.9406666666667,
          8.27
        ]
      },
      "id": "pr71454503"
    },
    {
      "type": "Feature",
      "properties": {
        "mag": 2.85,
        "place": "24 km N of Garrochales, Puerto Rico",
        "time": 1719955061070,
        "updated": 1719957175910,
        "tz": null,
        "url": "https://earthquake.usgs.gov/earthquakes/eventpage/pr71454508",
        "detail": "https://earthquake.usgs.gov/earthquakes/feed/v1.0/detail/pr71454508.geojson",
        "felt": null,
        "cdi": null,
        "mmi": null,
        "alert": null,
        "status": "reviewed",
        "tsunami": 0,
        "sig": 125,
        "net": "pr",
        "code": "71454508",
        "ids": ",pr71454508,",
        "sources": ",pr,",
        "types": ",origin,phase-data,",
        "nst": 14,
        "dmin": 0.2083,
        "rms": 0.3,
        "gap": 232,
        "magType": "md",
        "type": "earthquake",
        "title": "M 2.9 - 24 km N of Garrochales, Puerto Rico"
      },
      "geometry": {
        "type": "Point",
        "coordinates": [
          -66.6006666666667,
          18.6751666666667,
          23.62
        ]
      },
      "id": "pr71454508"
    }
  ],
  "bbox": [
    -179.4002,
    -54.019,
    0,
    166.8124,
    83.8535,
    620.597
  ]
}
