{
  "type": "FeatureCollection",
  "metadata": {
    "generated": 1656259208000,
    "url": "https://earthquake.usgs.gov/earthquakes/feed/v1.0/summary/2.5_day.geojson",
    "title": "USGS Magnitude 2.5+ Earthquakes, Past Day",
    "status": 200,
    "api": "1.10.3",
    "count": 37
  },
  "features": [
    {
      "type": "Feature",
      "properties": {
        "mag": 2.8,
        "place": "21 km ESE of Kelly, Wyoming",
        "time": 1656250823025,
        "updated": 1656254938040,
        "tz": null,
        "url": "https://earthquake.usgs.gov/earthquakes/eventpage/us7000hkdx",
        "detail": "https://earthquake.usgs.gov/earthquakes/feed/v1.0/detail/us7000hkdx.geojson",
        "felt": null,
        "cdi": null,
        "mmi": null,
        "alert": null,
        "status": "reviewed",
        "tsunami": 0,
        "sig": 121,
        "net": "us",
        "code": "7000hkdx",
        "ids": ",mb80549834,us7000hkdx,",
        "sources": ",mb,us,",
        "types": ",origin,phase-data,",
        "nst": null,
        "dmin": 0.173,
        "rms": 0.3,
        "gap": 114,
        "magType": "ml",
        "type": "earthquake",
        "title": "M 2.8 - 21 km ESE of Kelly, Wyoming"
      },
      "geometry": {
        "type": "Point",
        "coordinates": [
          -110.3967,
          43.5266,
          10.37
        ]
      },
      "id": "us7000hkdx"
    },
    {
      "type": "Feature",
      "properties": {
        "mag": 2.45,
        "place": "5 km SSW of Indios, Puerto Rico",
        "time": 1656250774500,
        "updated": 1656257516630,
        "tz": null,
        "url": "https://earthquake.usgs.gov/earthquakes/eventpage/pr71356123",
        "detail": "https://earthquake.usgs.gov/earthquakes/feed/v1.0/detail/pr71356123.geojson",
        "felt": null,
        "cdi": null,
        "mmi": null,
        "alert": null,
        "status": "reviewed",
        "tsunami": 0,
        "sig": 92,
        "net": "pr",
        "code": "71356123",
        "ids": ",pr71356123,",
        "sources": ",pr,",
        "types": ",origin,phase-data,",
        "nst": 26,
        "dmin": null,
        "rms": 0.23,
        "gap": 176,
        "magType": "md",
        "type": "earthquake",
        "title": "M 2.5 - 5 km SSW of Indios, Puerto Rico"
      },
      "geometry": {
        "type": "Point",
        "coordinates": [
          -66.8378333333333,
          17.946,
          14.86
        ]
      },
      "id": "pr71356123"
    },
    {
      "type": "Feature",
      "properties": {
        "mag": 3.35,
        "place": "102 km N of Charlotte Amalie, U.S. Virgin Islands",
        "time": 1656250711690,
        "updated": 1656256442880,
        "tz": null,
        "url": "https://earthquake.usgs.gov/earthquakes/eventpage/pr71356128",
        "detail": "https://earthquake.usgs.gov/earthquakes/feed/v1.0/detail/pr71356128.geojson",
        "felt": null,
        "cdi": null,
        "mmi": null,
        "alert": null,
        "status": "reviewed",
        "tsunami": 0,
        "sig": 173,
        "net": "pr",
        "code": "71356128",
        "ids": ",us7000hkdw,pr71356128,",
        "sources": ",us,pr,",
        "types": ",origin,phase-data,",
        "nst": 9,
        "dmin": null,
        "rms": 0.25,
        "gap": 326,
        "magType": "md",
        "type": "earthquake",
        "title": "M 3.4 - 102 km N of Charlotte Amalie, U.S. Virgin Islands"
      },
      "geometry": {
        "type": "Point",
        "coordinates": [
          -64.8625,
          19.2615,
          25.2
        ]
      },
      "id": "pr71356128"
    },
    {
      "type": "Feature",
      "properties": {
        "mag": 3.33,
        "place": "5 km SSW of Indios, Puerto Rico",
        "time": 1656250201640,
        "updated": 1656258893040,
        "tz": null,
        "url": "https://earthquake.usgs.gov/earthquakes/eventpage/pr2022177002",
        "detail": "https://earthquake.usgs.gov/earthquakes/feed/v1.0/detail/pr2022177002.geojson",
        "felt": 1,
        "cdi": 3.1,
        "mmi": null,
        "alert": null,
        "status": "reviewed",
        "tsunami": 0,
        "sig": 171,
        "net": "pr",
        "code": "2022177002",
        "ids": ",pr2022177002,us7000hkds,",
        "sources": ",pr,us,",
        "types": ",dyfi,origin,phase-data,",
        "nst": 22,
        "dmin": 0.0474,
        "rms": 0.17,
        "gap": 176,
        "magType": "md",
        "type": "earthquake",
        "title": "M 3.3 - 5 km SSW of Indios, Puerto Rico"
      },
      "geometry": {
        "type": "Point",
        "coordinates": [
          -66.8406,
          17.9476,
          14
        ]
      },
      "id": "pr2022177002"
    },
    {
      "type": "Feature",
      "properties": {
        "mag": 4,
        "place": "8 km S of Indios, Puerto Rico",
        "time": 1656249955471,
        "updated": 1656257781652,
        "tz": null,
        "url": "https://earthquake.usgs.gov/earthquakes/eventpage/us7000hkdp",
        "detail": "https://earthquake.usgs.gov/earthquakes/feed/v1.0/detail/us7000hkdp.geojson",
        "felt": 22,
        "cdi": 5.3,
        "mmi": 3.02,
        "alert": "green",
        "status": "reviewed",
        "tsunami": 0,
        "sig": 258,
        "net": "us",
        "code": "7000hkdp",
        "ids": ",us7000hkdp,",
        "sources": ",us,",
        "types": ",dyfi,losspager,origin,phase-data,shakemap,",
        "nst": null,
        "dmin": 0.133,
        "rms": 0.4,
        "gap": 160,
        "magType": "ml",
        "type": "earthquake",
        "title": "M 4.0 - 8 km S of Indios, Puerto Rico"
      },
      "geometry": {
        "type": "Point",
        "coordinates": [
          -66.8175,
          17.9188,
          22.97
        ]
      },
      "id": "us7000hkdp"
    },
    {
      "type": "Feature",
      "properties": {
        "mag": 2.8,
        "place": "13 km WSW of Akutan, Alaska",
        "time": 1656249214549,
        "updated": 1656252361040,
        "tz": null,
        "url": "https://earthquake.usgs.gov/earthquakes/eventpage/us7000hkdm",
        "detail": "https://earthquake.usgs.gov/earthquakes/feed/v1.0/detail/us7000hkdm.geojson",
        "felt": null,
        "cdi": null,
        "mmi": null,
        "alert": null,
        "status": "reviewed",
        "tsunami": 0,
        "sig": 121,
        "net": "us",
        "code": "7000hkdm",
        "ids": ",us7000hkdm,",
        "sources": ",us,",
        "types": ",origin,phase-data,",
        "nst": null,
        "dmin": 0.084,
        "rms": 0.4,
        "gap": 167,
        "magType": "ml",
        "type": "earthquake",
        "title": "M 2.8 - 13 km WSW of Akutan, Alaska"
      },
      "geometry": {
        "type": "Point",
        "coordinates": [
          -165.9698,
          54.0847,
          110.09
        ]
      },
      "id": "us7000hkdm"
    },
    {
      "type": "Feature",
      "properties": {
        "mag": 4.9,
        "place": "54 km NE of R훮var, Iran",
        "time": 1656248837692,
        "updated": 1656252162014,
        "tz": null,
        "url": "https://earthquake.usgs.gov/earthquakes/eventpage/us7000hkdl",
        "detail": "https://earthquake.usgs.gov/earthquakes/feed/v1.0/detail/us7000hkdl.geojson",
        "felt": 2,
        "cdi": 3.1,
        "mmi": null,
        "alert": null,
        "status": "reviewed",
        "tsunami": 0,
        "sig": 370,
        "net": "us",
        "code": "7000hkdl",
        "ids": ",us7000hkdl,",
        "sources": ",us,",
        "types": ",dyfi,origin,phase-data,",
        "nst": null,
        "dmin": 6.678,
        "rms": 0.62,
        "gap": 70,
        "magType": "mb",
        "type": "earthquake",
        "title": "M 4.9 - 54 km NE of R훮var, Iran"
      },
      "geometry": {
        "type": "Point",
        "coordinates": [
          57.237,
          31.5862,
          10
        ]
      },
      "id": "us7000hkdl"
    },
    {
      "type": "Feature",
      "properties": {
        "mag": 2.55,
        "place": "4 km SSW of P훮hala, Hawaii",
        "time": 1656248510820,
        "updated": 1656248841570,
        "tz": null,
        "url": "https://earthquake.usgs.gov/earthquakes/eventpage/hv73056367",
        "detail": "https://earthquake.usgs.gov/earthquakes/feed/v1.0/detail/hv73056367.geojson",
        "felt": null,
        "cdi": null,
        "mmi": null,
        "alert": null,
        "status": "automatic",
        "tsunami": 0,
        "sig": 100,
        "net": "hv",
        "code": "73056367",
        "ids": ",hv73056367,",
        "sources": ",hv,",
        "types": ",origin,phase-data,",
        "nst": 24,
        "dmin": null,
        "rms": 0.230000004,
        "gap": 152,
        "magType": "ml",
        "type": "earthquake",
        "title": "M 2.6 - 4 km SSW of P훮hala, Hawaii"
      },
      "geometry": {
        "type": "Point",
        "coordinates": [
          -155.493499755859,
          19.16233253479,
          34.810001373291
        ]
      },
      "id": "hv73056367"
    },
    {
      "type": "Feature",
      "properties": {
        "mag": 4.6,
        "place": "2 km NNE of Honmachi, Japan",
        "time": 1656247488925,
        "updated": 1656252291298,
        "tz": null,
        "url": "https://earthquake.usgs.gov/earthquakes/eventpage/us7000hkdf",
        "detail": "https://earthquake.usgs.gov/earthquakes/feed/v1.0/detail/us7000hkdf.geojson",
        "felt": 3,
        "cdi": 3.8,
        "mmi": null,
        "alert": null,
        "status": "reviewed",
        "tsunami": 0,
        "sig": 327,
        "net": "us",
        "code": "7000hkdf",
        "ids": ",us7000hkdf,",
        "sources": ",us,",
        "types": ",dyfi,origin,phase-data,",
        "nst": null,
        "dmin": 1.023,
        "rms": 0.4,
        "gap": 93,
        "magType": "mb",
        "type": "earthquake",
        "title": "M 4.6 - 2 km NNE of Honmachi, Japan"
      },
      "geometry": {
        "type": "Point",
        "coordinates": [
          130.6153,
          32.5261,
          10
        ]
      },
      "id": "us7000hkdf"
    },
    {
      "type": "Feature",
      "properties": {
        "mag": 4.4,
        "place": "Bali region, Indonesia",
        "time": 1656246334035,
        "updated": 1656250651192,
        "tz": null,
        "url": "https://earthquake.usgs.gov/earthquakes/eventpage/us7000hkde",
        "detail": "https://earthquake.usgs.gov/earthquakes/feed/v1.0/detail/us7000hkde.geojson",
        "felt": 9,
        "cdi": 3.8,
        "mmi": null,
        "alert": null,
        "status": "reviewed",
        "tsunami": 0,
        "sig": 301,
        "net": "us",
        "code": "7000hkde",
        "ids": ",us7000hkde,",
        "sources": ",us,",
        "types": ",dyfi,origin,phase-data,",
        "nst": null,
        "dmin": 1.134,
        "rms": 0.56,
        "gap": 75,
        "magType": "mb",
        "type": "earthquake",
        "title": "M 4.4 - Bali region, Indonesia"
      },
      "geometry": {
        "type": "Point",
        "coordinates": [
          115.279,
          -8.6838,
          113.12
        ]
      },
      "id": "us7000hkde"
    },
    {
      "type": "Feature",
      "properties": {
        "mag": 4.1,
        "place": "12 km SE of Sullana, Peru",
        "time": 1656235675513,
        "updated": 1656237486040,
        "tz": null,
        "url": "https://earthquake.usgs.gov/earthquakes/eventpage/us7000hkci",
        "detail": "https://earthquake.usgs.gov/earthquakes/feed/v1.0/detail/us7000hkci.geojson",
        "felt": null,
        "cdi": null,
        "mmi": null,
        "alert": null,
        "status": "reviewed",
        "tsunami": 0,
        "sig": 259,
        "net": "us",
        "code": "7000hkci",
        "ids": ",us7000hkci,",
        "sources": ",us,",
        "types": ",origin,phase-data,",
        "nst": null,
        "dmin": 3.865,
        "rms": 0.53,
        "gap": 159,
        "magType": "mb",
        "type": "earthquake",
        "title": "M 4.1 - 12 km SE of Sullana, Peru"
      },
      "geometry": {
        "type": "Point",
        "coordinates": [
          -80.6019,
          -4.9736,
          57.29
        ]
      },
      "id": "us7000hkci"
    },
    {
      "type": "Feature",
      "properties": {
        "mag": 2.6,
        "place": "56 km S of Whites City, New Mexico",
        "time": 1656235433180,
        "updated": 1656235830040,
        "tz": null,
        "url": "https://earthquake.usgs.gov/earthquakes/eventpage/us7000hkcg",
        "detail": "https://earthquake.usgs.gov/earthquakes/feed/v1.0/detail/us7000hkcg.geojson",
        "felt": null,
        "cdi": null,
        "mmi": null,
        "alert": null,
        "status": "reviewed",
        "tsunami": 0,
        "sig": 104,
        "net": "us",
        "code": "7000hkcg",
        "ids": ",us7000hkcg,",
        "sources": ",us,",
        "types": ",origin,phase-data,",
        "nst": null,
        "dmin": 0.103,
        "rms": 0.31,
        "gap": 116,
        "magType": "ml",
        "type": "earthquake",
        "title": "M 2.6 - 56 km S of Whites City, New Mexico"
      },
      "geometry": {
        "type": "Point",
        "coordinates": [
          -104.3795,
          31.6669,
          5
        ]
      },
      "id": "us7000hkcg"
    },
    {
      "type": "Feature",
      "properties": {
        "mag": 4.9,
        "place": "109 km WNW of Isangel, Vanuatu",
        "time": 1656230988851,
        "updated": 1656231963040,
        "tz": null,
        "url": "https://earthquake.usgs.gov/earthquakes/eventpage/us7000hkc6",
        "detail": "https://earthquake.usgs.gov/earthquakes/feed/v1.0/detail/us7000hkc6.geojson",
        "felt": null,
        "cdi": null,
        "mmi": null,
        "alert": null,
        "status": "reviewed",
        "tsunami": 0,
        "sig": 369,
        "net": "us",
        "code": "7000hkc6",
        "ids": ",us7000hkc6,",
        "sources": ",us,",
        "types": ",origin,phase-data,",
        "nst": null,
        "dmin": 3.367,
        "rms": 0.49,
        "gap": 115,
        "magType": "mb",
        "type": "earthquake",
        "title": "M 4.9 - 109 km WNW of Isangel, Vanuatu"
      },
      "geometry": {
        "type": "Point",
        "coordinates": [
          168.3117,
          -19.1797,
          27.85
        ]
      },
      "id": "us7000hkc6"
    },
    {
      "type": "Feature",
      "properties": {
        "mag": 3.64,
        "place": "5 km ENE of Punta Cana, Dominican Republic",
        "time": 1656230603780,
        "updated": 1656245703843,
        "tz": null,
        "url": "https://earthquake.usgs.gov/earthquakes/eventpage/pr2022177000",
        "detail": "https://earthquake.usgs.gov/earthquakes/feed/v1.0/detail/pr2022177000.geojson",
        "felt": 1,
        "cdi": 2,
        "mmi": null,
        "alert": null,
        "status": "reviewed",
        "tsunami": 0,
        "sig": 204,
        "net": "pr",
        "code": "2022177000",
        "ids": ",pr2022177000,",
        "sources": ",pr,",
        "types": ",dyfi,origin,phase-data,",
        "nst": 21,
        "dmin": 0.0874,
        "rms": 0.04,
        "gap": 286,
        "magType": "md",
        "type": "earthquake",
        "title": "M 3.6 - 5 km ENE of Punta Cana, Dominican Republic"
      },
      "geometry": {
        "type": "Point",
        "coordinates": [
          -68.3561,
          18.5976,
          125
        ]
      },
      "id": "pr2022177000"
    },
    {
      "type": "Feature",
      "properties": {
        "mag": 4.6,
        "place": "6 km NNE of El Tejar, Guatemala",
        "time": 1656227101489,
        "updated": 1656228099040,
        "tz": null,
        "url": "https://earthquake.usgs.gov/earthquakes/eventpage/us7000hkby",
        "detail": "https://earthquake.usgs.gov/earthquakes/feed/v1.0/detail/us7000hkby.geojson",
        "felt": null,
        "cdi": null,
        "mmi": null,
        "alert": null,
        "status": "reviewed",
        "tsunami": 0,
        "sig": 326,
        "net": "us",
        "code": "7000hkby",
        "ids": ",us7000hkby,",
        "sources": ",us,",
        "types": ",origin,phase-data,",
        "nst": null,
        "dmin": 0.315,
        "rms": 0.68,
        "gap": 143,
        "magType": "mb",
        "type": "earthquake",
        "title": "M 4.6 - 6 km NNE of El Tejar, Guatemala"
      },
      "geometry": {
        "type": "Point",
        "coordinates": [
          -90.7706,
          14.706,
          193
        ]
      },
      "id": "us7000hkby"
    },
    {
      "type": "Feature",
      "properties": {
        "mag": 2.47,
        "place": "5km ENE of Calexico, CA",
        "time": 1656225145740,
        "updated": 1656225805550,
        "tz": null,
        "url": "https://earthquake.usgs.gov/earthquakes/eventpage/ci40291608",
        "detail": "https://earthquake.usgs.gov/earthquakes/feed/v1.0/detail/ci40291608.geojson",
        "felt": null,
        "cdi": null,
        "mmi": null,
        "alert": null,
        "status": "automatic",
        "tsunami": 0,
        "sig": 94,
        "net": "ci",
        "code": "40291608",
        "ids": ",ci40291608,",
        "sources": ",ci,",
        "types": ",focal-mechanism,nearby-cities,origin,phase-data,scitech-link,",
        "nst": 25,
        "dmin": 0.06969,
        "rms": 0.27,
        "gap": 54,
        "magType": "ml",
        "type": "earthquake",
        "title": "M 2.5 - 5km ENE of Calexico, CA"
      },
      "geometry": {
        "type": "Point",
        "coordinates": [
          -115.4501667,
          32.7013333,
          11.22
        ]
      },
      "id": "ci40291608"
    },
    {
      "type": "Feature",
      "properties": {
        "mag": 2.57,
        "place": "3 km WSW of Indios, Puerto Rico",
        "time": 1656223409050,
        "updated": 1656225045080,
        "tz": null,
        "url": "https://earthquake.usgs.gov/earthquakes/eventpage/pr71356033",
        "detail": "https://earthquake.usgs.gov/earthquakes/feed/v1.0/detail/pr71356033.geojson",
        "felt": null,
        "cdi": null,
        "mmi": null,
        "alert": null,
        "status": "reviewed",
        "tsunami": 0,
        "sig": 102,
        "net": "pr",
        "code": "71356033",
        "ids": ",pr71356033,",
        "sources": ",pr,",
        "types": ",origin,phase-data,",
        "nst": 18,
        "dmin": null,
        "rms": 0.27,
        "gap": 147,
        "magType": "md",
        "type": "earthquake",
        "title": "M 2.6 - 3 km WSW of Indios, Puerto Rico"
      },
      "geometry": {
        "type": "Point",
        "coordinates": [
          -66.8521666666667,
          17.983,
          15.48
        ]
      },
      "id": "pr71356033"
    },
    {
      "type": "Feature",
      "properties": {
        "mag": 4.4,
        "place": "117 km E of Shikotan, Russia",
        "time": 1656222660445,
        "updated": 1656224237040,
        "tz": null,
        "url": "https://earthquake.usgs.gov/earthquakes/eventpage/us7000hkbf",
        "detail": "https://earthquake.usgs.gov/earthquakes/feed/v1.0/detail/us7000hkbf.geojson",
        "felt": null,
        "cdi": null,
        "mmi": null,
        "alert": null,
        "status": "reviewed",
        "tsunami": 0,
        "sig": 298,
        "net": "us",
        "code": "7000hkbf",
        "ids": ",us7000hkbf,",
        "sources": ",us,",
        "types": ",origin,phase-data,",
        "nst": null,
        "dmin": 4.037,
        "rms": 0.59,
        "gap": 164,
        "magType": "mb",
        "type": "earthquake",
        "title": "M 4.4 - 117 km E of Shikotan, Russia"
      },
      "geometry": {
        "type": "Point",
        "coordinates": [
          148.1757,
          43.8554,
          50.86
        ]
      },
      "id": "us7000hkbf"
    },
    {
      "type": "Feature",
      "properties": {
        "mag": 3.4,
        "place": "6 km E of Elgin, South Carolina",
        "time": 1656221514630,
        "updated": 1656259150445,
        "tz": null,
        "url": "https://earthquake.usgs.gov/earthquakes/eventpage/se60400941",
        "detail": "https://earthquake.usgs.gov/earthquakes/feed/v1.0/detail/se60400941.geojson",
        "felt": 3330,
        "cdi": 4.7,
        "mmi": null,
        "alert": null,
        "status": "reviewed",
        "tsunami": 0,
        "sig": 648,
        "net": "se",
        "code": "60400941",
        "ids": ",se60400941,us7000hkb7,",
        "sources": ",se,us,",
        "types": ",dyfi,moment-tensor,origin,phase-data,",
        "nst": 22,
        "dmin": 0.03854,
        "rms": 0.34,
        "gap": 63,
        "magType": "mw",
        "type": "earthquake",
        "title": "M 3.4 - 6 km E of Elgin, South Carolina"
      },
      "geometry": {
        "type": "Point",
        "coordinates": [
          -80.7246667,
          34.1668333,
          3.3
        ]
      },
      "id": "se60400941"
    },
    {
      "type": "Feature",
      "properties": {
        "mag": 4.7,
        "place": "South Sandwich Islands region",
        "time": 1656220101032,
        "updated": 1656223204040,
        "tz": null,
        "url": "https://earthquake.usgs.gov/earthquakes/eventpage/us7000hkbc",
        "detail": "https://earthquake.usgs.gov/earthquakes/feed/v1.0/detail/us7000hkbc.geojson",
        "felt": null,
        "cdi": null,
        "mmi": null,
        "alert": null,
        "status": "reviewed",
        "tsunami": 0,
        "sig": 340,
        "net": "us",
        "code": "7000hkbc",
        "ids": ",us7000hkbc,",
        "sources": ",us,",
        "types": ",origin,phase-data,",
        "nst": null,
        "dmin": 14.328,
        "rms": 0.88,
        "gap": 81,
        "magType": "mb",
        "type": "earthquake",
        "title": "M 4.7 - South Sandwich Islands region"
      },
      "geometry": {
        "type": "Point",
        "coordinates": [
          -25.6331,
          -60.5647,
          10
        ]
      },
      "id": "us7000hkbc"
    },
    {
      "type": "Feature",
      "properties": {
        "mag": 4.1,
        "place": "93 km ENE of Iquique, Chile",
        "time": 1656218992825,
        "updated": 1656221383561,
        "tz": null,
        "url": "https://earthquake.usgs.gov/earthquakes/eventpage/us7000hkay",
        "detail": "https://earthquake.usgs.gov/earthquakes/feed/v1.0/detail/us7000hkay.geojson",
        "felt": 3,
        "cdi": 2.5,
        "mmi": null,
        "alert": null,
        "status": "reviewed",
        "tsunami": 0,
        "sig": 259,
        "net": "us",
        "code": "7000hkay",
        "ids": ",us7000hkay,",
        "sources": ",us,",
        "types": ",dyfi,origin,phase-data,",
        "nst": null,
        "dmin": 0.211,
        "rms": 0.45,
        "gap": 89,
        "magType": "mb",
        "type": "earthquake",
        "title": "M 4.1 - 93 km ENE of Iquique, Chile"
      },
      "geometry": {
        "type": "Point",
        "coordinates": [
          -69.4004,
          -19.7523,
          93.35
        ]
      },
      "id": "us7000hkay"
    },
    {
      "type": "Feature",
      "properties": {
        "mag": 4.3,
        "place": "Greenland Sea",
        "time": 1656213621871,
        "updated": 1656217818040,
        "tz": null,
        "url": "https://earthquake.usgs.gov/earthquakes/eventpage/us7000hkaf",
        "detail": "https://earthquake.usgs.gov/earthquakes/feed/v1.0/detail/us7000hkaf.geojson",
        "felt": null,
        "cdi": null,
        "mmi": null,
        "alert": null,
        "status": "reviewed",
        "tsunami": 0,
        "sig": 284,
        "net": "us",
        "code": "7000hkaf",
        "ids": ",us7000hkaf,",
        "sources": ",us,",
        "types": ",origin,phase-data,",
        "nst": null,
        "dmin": 11.576,
        "rms": 0.55,
        "gap": 121,
        "magType": "mb",
        "type": "earthquake",
        "title": "M 4.3 - Greenland Sea"
      },
      "geometry": {
        "type": "Point",
        "coordinates": [
          3.7585,
          79.7235,
          10
        ]
      },
      "id": "us7000hkaf"
    },
    {
      "type": "Feature",
      "properties": {
        "mag": 5.7,
        "place": "108 km S of Atico, Peru",
        "time": 1656208955786,
        "updated": 1656217571128,
        "tz": null,
        "url": "https://earthquake.usgs.gov/earthquakes/eventpage/us7000hk9n",
        "detail": "https://earthquake.usgs.gov/earthquakes/feed/v1.0/detail/us7000hk9n.geojson",
        "felt": 3,
        "cdi": 5,
        "mmi": 3.611,
        "alert": "green",
        "status": "reviewed",
        "tsunami": 0,
        "sig": 501,
        "net": "us",
        "code": "7000hk9n",
        "ids": ",us7000hk9n,",
        "sources": ",us,",
        "types": ",dyfi,losspager,moment-tensor,origin,phase-data,shakemap,",
        "nst": null,
        "dmin": 3.472,
        "rms": 0.98,
        "gap": 49,
        "magType": "mww",
        "type": "earthquake",
        "title": "M 5.7 - 108 km S of Atico, Peru"
      },
      "geometry": {
        "type": "Point",
        "coordinates": [
          -73.7663,
          -17.1756,
          15.1
        ]
      },
      "id": "us7000hk9n"
    },
    {
      "type": "Feature",
      "properties": {
        "mag": 4.8,
        "place": "South Sandwich Islands region",
        "time": 1656208476915,
        "updated": 1656209683040,
        "tz": null,
        "url": "https://earthquake.usgs.gov/earthquakes/eventpage/us7000hk9p",
        "detail": "https://earthquake.usgs.gov/earthquakes/feed/v1.0/detail/us7000hk9p.geojson",
        "felt": null,
        "cdi": null,
        "mmi": null,
        "alert": null,
        "status": "reviewed",
        "tsunami": 0,
        "sig": 354,
        "net": "us",
        "code": "7000hk9p",
        "ids": ",us7000hk9p,",
        "sources": ",us,",
        "types": ",origin,phase-data,",
        "nst": null,
        "dmin": 16.655,
        "rms": 0.5,
        "gap": 71,
        "magType": "mb",
        "type": "earthquake",
        "title": "M 4.8 - South Sandwich Islands region"
      },
      "geometry": {
        "type": "Point",
        "coordinates": [
          -26.9125,
          -56.1603,
          67.93
        ]
      },
      "id": "us7000hk9p"
    },
    {
      "type": "Feature",
      "properties": {
        "mag": 2.46,
        "place": "4 km SW of Indios, Puerto Rico",
        "time": 1656204895390,
        "updated": 1656206821930,
        "tz": null,
        "url": "https://earthquake.usgs.gov/earthquakes/eventpage/pr71355988",
        "detail": "https://earthquake.usgs.gov/earthquakes/feed/v1.0/detail/pr71355988.geojson",
        "felt": null,
        "cdi": null,
        "mmi": null,
        "alert": null,
        "status": "reviewed",
        "tsunami": 0,
        "sig": 93,
        "net": "pr",
        "code": "71355988",
        "ids": ",pr71355988,",
        "sources": ",pr,",
        "types": ",origin,phase-data,",
        "nst": 10,
        "dmin": null,
        "rms": 0.16,
        "gap": 170,
        "magType": "md",
        "type": "earthquake",
        "title": "M 2.5 - 4 km SW of Indios, Puerto Rico"
      },
      "geometry": {
        "type": "Point",
        "coordinates": [
          -66.847,
          17.9626666666667,
          13.62
        ]
      },
      "id": "pr71355988"
    },
    {
      "type": "Feature",
      "properties": {
        "mag": 4,
        "place": "41 km SSW of Jurm, Afghanistan",
        "time": 1656191521739,
        "updated": 1656192224040,
        "tz": null,
        "url": "https://earthquake.usgs.gov/earthquakes/eventpage/us7000hk8p",
        "detail": "https://earthquake.usgs.gov/earthquakes/feed/v1.0/detail/us7000hk8p.geojson",
        "felt": null,
        "cdi": null,
        "mmi": null,
        "alert": null,
        "status": "reviewed",
        "tsunami": 0,
        "sig": 246,
        "net": "us",
        "code": "7000hk8p",
        "ids": ",us7000hk8p,",
        "sources": ",us,",
        "types": ",origin,phase-data,",
        "nst": null,
        "dmin": 0.635,
        "rms": 0.42,
        "gap": 112,
        "magType": "mb",
        "type": "earthquake",
        "title": "M 4.0 - 41 km SSW of Jurm, Afghanistan"
      },
      "geometry": {
        "type": "Point",
        "coordinates": [
          70.7385,
          36.5029,
          141.79
        ]
      },
      "id": "us7000hk8p"
    },
    {
      "type": "Feature",
      "properties": {
        "mag": 2.63,
        "place": "2 km SE of Maria Antonia, Puerto Rico",
        "time": 1656191252900,
        "updated": 1656192785550,
        "tz": null,
        "url": "https://earthquake.usgs.gov/earthquakes/eventpage/pr71355973",
        "detail": "https://earthquake.usgs.gov/earthquakes/feed/v1.0/detail/pr71355973.geojson",
        "felt": null,
        "cdi": null,
        "mmi": null,
        "alert": null,
        "status": "reviewed",
        "tsunami": 0,
        "sig": 106,
        "net": "pr",
        "code": "71355973",
        "ids": ",pr71355973,",
        "sources": ",pr,",
        "types": ",origin,phase-data,",
        "nst": 12,
        "dmin": null,
        "rms": 0.12,
        "gap": 201,
        "magType": "md",
        "type": "earthquake",
        "title": "M 2.6 - 2 km SE of Maria Antonia, Puerto Rico"
      },
      "geometry": {
        "type": "Point",
        "coordinates": [
          -66.8736666666667,
          17.9638333333333,
          9.91
        ]
      },
      "id": "pr71355973"
    },
    {
      "type": "Feature",
      "properties": {
        "mag": 4.1,
        "place": "62 km WNW of San Antonio de los Cobres, Argentina",
        "time": 1656189064776,
        "updated": 1656195539040,
        "tz": null,
        "url": "https://earthquake.usgs.gov/earthquakes/eventpage/us7000hk8j",
        "detail": "https://earthquake.usgs.gov/earthquakes/feed/v1.0/detail/us7000hk8j.geojson",
        "felt": null,
        "cdi": null,
        "mmi": null,
        "alert": null,
        "status": "reviewed",
        "tsunami": 0,
        "sig": 259,
        "net": "us",
        "code": "7000hk8j",
        "ids": ",us7000hk8j,",
        "sources": ",us,",
        "types": ",origin,phase-data,",
        "nst": null,
        "dmin": 1.601,
        "rms": 0.66,
        "gap": 92,
        "magType": "mb",
        "type": "earthquake",
        "title": "M 4.1 - 62 km WNW of San Antonio de los Cobres, Argentina"
      },
      "geometry": {
        "type": "Point",
        "coordinates": [
          -66.9082,
          -24.0539,
          190.31
        ]
      },
      "id": "us7000hk8j"
    },
    {
      "type": "Feature",
      "properties": {
        "mag": 4.5,
        "place": "5 km SE of Mangili, Philippines",
        "time": 1656188577758,
        "updated": 1656195130040,
        "tz": null,
        "url": "https://earthquake.usgs.gov/earthquakes/eventpage/us7000hk8i",
        "detail": "https://earthquake.usgs.gov/earthquakes/feed/v1.0/detail/us7000hk8i.geojson",
        "felt": null,
        "cdi": null,
        "mmi": null,
        "alert": null,
        "status": "reviewed",
        "tsunami": 0,
        "sig": 312,
        "net": "us",
        "code": "7000hk8i",
        "ids": ",us7000hk8i,",
        "sources": ",us,",
        "types": ",origin,phase-data,",
        "nst": null,
        "dmin": 1.1,
        "rms": 0.7,
        "gap": 117,
        "magType": "mb",
        "type": "earthquake",
        "title": "M 4.5 - 5 km SE of Mangili, Philippines"
      },
      "geometry": {
        "type": "Point",
        "coordinates": [
          125.7253,
          5.9714,
          145.46
        ]
      },
      "id": "us7000hk8i"
    },
    {
      "type": "Feature",
      "properties": {
        "mag": 2.95,
        "place": "5 km ENE of Oso, Washington",
        "time": 1656188320160,
        "updated": 1656254826448,
        "tz": null,
        "url": "https://earthquake.usgs.gov/earthquakes/eventpage/uw61846212",
        "detail": "https://earthquake.usgs.gov/earthquakes/feed/v1.0/detail/uw61846212.geojson",
        "felt": 42,
        "cdi": 3.8,
        "mmi": null,
        "alert": null,
        "status": "reviewed",
        "tsunami": 0,
        "sig": 150,
        "net": "uw",
        "code": "61846212",
        "ids": ",uw61846212,us7000hk8g,",
        "sources": ",uw,us,",
        "types": ",dyfi,origin,phase-data,",
        "nst": 28,
        "dmin": 0.1078,
        "rms": 0.25,
        "gap": 54,
        "magType": "ml",
        "type": "earthquake",
        "title": "M 3.0 - 5 km ENE of Oso, Washington"
      },
      "geometry": {
        "type": "Point",
        "coordinates": [
          -121.8635,
          48.29416666666667,
          6.29
        ]
      },
      "id": "uw61846212"
    },
    {
      "type": "Feature",
      "properties": {
        "mag": 3.3,
        "place": "9 km E of Delmas, South Africa",
        "time": 1656188071638,
        "updated": 1656216985932,
        "tz": null,
        "url": "https://earthquake.usgs.gov/earthquakes/eventpage/us7000hkap",
        "detail": "https://earthquake.usgs.gov/earthquakes/feed/v1.0/detail/us7000hkap.geojson",
        "felt": 1,
        "cdi": 3.9,
        "mmi": null,
        "alert": null,
        "status": "reviewed",
        "tsunami": 0,
        "sig": 168,
        "net": "us",
        "code": "7000hkap",
        "ids": ",us7000hkap,",
        "sources": ",us,",
        "types": ",dyfi,origin,phase-data,",
        "nst": null,
        "dmin": 3.085,
        "rms": 0.94,
        "gap": 275,
        "magType": "ml",
        "type": "earthquake",
        "title": "M 3.3 - 9 km E of Delmas, South Africa"
      },
      "geometry": {
        "type": "Point",
        "coordinates": [
          28.7736,
          -26.1558,
          10
        ]
      },
      "id": "us7000hkap"
    },
    {
      "type": "Feature",
      "properties": {
        "mag": 2.5,
        "place": "33 km WSW of Mentone, Texas",
        "time": 1656185377060,
        "updated": 1656194047040,
        "tz": null,
        "url": "https://earthquake.usgs.gov/earthquakes/eventpage/us7000hk87",
        "detail": "https://earthquake.usgs.gov/earthquakes/feed/v1.0/detail/us7000hk87.geojson",
        "felt": null,
        "cdi": null,
        "mmi": null,
        "alert": null,
        "status": "reviewed",
        "tsunami": 0,
        "sig": 96,
        "net": "us",
        "code": "7000hk87",
        "ids": ",us7000hk87,",
        "sources": ",us,",
        "types": ",origin,phase-data,",
        "nst": null,
        "dmin": 0.243,
        "rms": 0.38,
        "gap": 54,
        "magType": "mb_lg",
        "type": "earthquake",
        "title": "M 2.5 - 33 km WSW of Mentone, Texas"
      },
      "geometry": {
        "type": "Point",
        "coordinates": [
          -103.9348,
          31.6079,
          3.69
        ]
      },
      "id": "us7000hk87"
    },
    {
      "type": "Feature",
      "properties": {
        "mag": 4.5,
        "place": "South Sandwich Islands region",
        "time": 1656184236467,
        "updated": 1656192535040,
        "tz": null,
        "url": "https://earthquake.usgs.gov/earthquakes/eventpage/us7000hk85",
        "detail": "https://earthquake.usgs.gov/earthquakes/feed/v1.0/detail/us7000hk85.geojson",
        "felt": null,
        "cdi": null,
        "mmi": null,
        "alert": null,
        "status": "reviewed",
        "tsunami": 0,
        "sig": 312,
        "net": "us",
        "code": "7000hk85",
        "ids": ",us7000hk85,",
        "sources": ",us,",
        "types": ",origin,phase-data,",
        "nst": null,
        "dmin": 15.912,
        "rms": 0.64,
        "gap": 79,
        "magType": "mb",
        "type": "earthquake",
        "title": "M 4.5 - South Sandwich Islands region"
      },
      "geometry": {
        "type": "Point",
        "coordinates": [
          -25.0482,
          -58.6246,
          24.81
        ]
      },
      "id": "us7000hk85"
    },
    {
      "type": "Feature",
      "properties": {
        "mag": 4.3,
        "place": "285 km E of Levuka, Fiji",
        "time": 1656183630653,
        "updated": 1656191642040,
        "tz": null,
        "url": "https://earthquake.usgs.gov/earthquakes/eventpage/us7000hk84",
        "detail": "https://earthquake.usgs.gov/earthquakes/feed/v1.0/detail/us7000hk84.geojson",
        "felt": null,
        "cdi": null,
        "mmi": null,
        "alert": null,
        "status": "reviewed",
        "tsunami": 0,
        "sig": 284,
        "net": "us",
        "code": "7000hk84",
        "ids": ",us7000hk84,",
        "sources": ",us,",
        "types": ",origin,phase-data,",
        "nst": null,
        "dmin": 3.796,
        "rms": 0.83,
        "gap": 115,
        "magType": "mb",
        "type": "earthquake",
        "title": "M 4.3 - 285 km E of Levuka, Fiji"
      },
      "geometry": {
        "type": "Point",
        "coordinates": [
          -177.9868,
          -18.1961,
          584.11
        ]
      },
      "id": "us7000hk84"
    },
    {
      "type": "Feature",
      "properties": {
        "mag": 2.6,
        "place": "2 km SE of Lindsay, Texas",
        "time": 1656176709901,
        "updated": 1656179528040,
        "tz": null,
        "url": "https://earthquake.usgs.gov/earthquakes/eventpage/us7000hk7l",
        "detail": "https://earthquake.usgs.gov/earthquakes/feed/v1.0/detail/us7000hk7l.geojson",
        "felt": null,
        "cdi": null,
        "mmi": null,
        "alert": null,
        "status": "reviewed",
        "tsunami": 0,
        "sig": 104,
        "net": "us",
        "code": "7000hk7l",
        "ids": ",us7000hk7l,",
        "sources": ",us,",
        "types": ",origin,phase-data,",
        "nst": null,
        "dmin": 0.297,
        "rms": 0.47,
        "gap": 38,
        "magType": "ml",
        "type": "earthquake",
        "title": "M 2.6 - 2 km SE of Lindsay, Texas"
      },
      "geometry": {
        "type": "Point",
        "coordinates": [
          -103.5199,
          31.3508,
          5
        ]
      },
      "id": "us7000hk7l"
    },
    {
      "type": "Feature",
      "properties": {
        "mag": 4.4,
        "place": "16 km NNE of The Valley, Anguilla",
        "time": 1656175545336,
        "updated": 1656212326604,
        "tz": null,
        "url": "https://earthquake.usgs.gov/earthquakes/eventpage/us7000hk7i",
        "detail": "https://earthquake.usgs.gov/earthquakes/feed/v1.0/detail/us7000hk7i.geojson",
        "felt": 16,
        "cdi": 3.4,
        "mmi": null,
        "alert": null,
        "status": "reviewed",
        "tsunami": 0,
        "sig": 303,
        "net": "us",
        "code": "7000hk7i",
        "ids": ",us7000hk7i,",
        "sources": ",us,",
        "types": ",dyfi,origin,phase-data,",
        "nst": null,
        "dmin": 0.304,
        "rms": 0.49,
        "gap": 143,
        "magType": "mb",
        "type": "earthquake",
        "title": "M 4.4 - 16 km NNE of The Valley, Anguilla"
      },
      "geometry": {
        "type": "Point",
        "coordinates": [
          -62.9735,
          18.3403,
          32.78
        ]
      },
      "id": "us7000hk7i"
    },
    {
      "type": "Feature",
      "properties": {
        "mag": 4.8,
        "place": "76 km ENE of San Ignacio, Peru",
        "time": 1656173492900,
        "updated": 1656175260040,
        "tz": null,
        "url": "https://earthquake.usgs.gov/earthquakes/eventpage/us7000hk7c",
        "detail": "https://earthquake.usgs.gov/earthquakes/feed/v1.0/detail/us7000hk7c.geojson",
        "felt": null,
        "cdi": null,
        "mmi": null,
        "alert": null,
        "status": "reviewed",
        "tsunami": 0,
        "sig": 354,
        "net": "us",
        "code": "7000hk7c",
        "ids": ",us7000hk7c,",
        "sources": ",us,",
        "types": ",origin,phase-data,",
        "nst": null,
        "dmin": 3.318,
        "rms": 1.07,
        "gap": 143,
        "magType": "mb",
        "type": "earthquake",
        "title": "M 4.8 - 76 km ENE of San Ignacio, Peru"
      },
      "geometry": {
        "type": "Point",
        "coordinates": [
          -78.3932,
          -4.813,
          69.47
        ]
      },
      "id": "us7000hk7c"
    }
  ],
  "bbox": [
    -177.9868,
    -60.5647,
    3.3,
    168.3117,
    79.7235,
    584.11
  ]
}
